ferrous_cat_finance/__init__.py
ferrous_cat_finance/db-creation.sql
ferrous_cat_finance/feline-upheaval.sql
ferrous_cat_finance/feline-values.sql
ferrous_cat_finance/feline_values.py
ferrous_cat_finance/ferrous-cat-finance.db
ferrous_cat_finance/financial_app.py
ferrous_cat_finance/pers_pref.json
ferrous_cat_finance/start-app.sh
ferrous_cat_finance/data/Category.py
ferrous_cat_finance/data/Error.py
ferrous_cat_finance/data/SecondParty.py
ferrous_cat_finance/data/Transaction.py
ferrous_cat_finance/data/ledger_object.py
ferrous_cat_finance/data/pdf_export.py
ferrous_cat_finance/data/report_organizer.py
ferrous_cat_finance/output-files/.gitignore
ferrous_cat_finance/scripts/predefinitions.py
ferrous_cat_finance/storage/CategoryTable.py
ferrous_cat_finance/storage/Database.py
ferrous_cat_finance/storage/SecondPartyTable.py
ferrous_cat_finance/storage/TestData.py
ferrous_cat_finance/storage/TransactionTable.py
ferrous_cat_finance/storage/ledger_table.py
ferrous_cat_finance/storage/record_search.py
ferrous_cat_finance/ui/Category.py
ferrous_cat_finance/ui/Common.py
ferrous_cat_finance/ui/Font.py
ferrous_cat_finance/ui/Main.py
ferrous_cat_finance/ui/Reports.py
ferrous_cat_finance/ui/Transactions.py
ferrous_cat_finance-0.1.dist-info/METADATA
ferrous_cat_finance-0.1.dist-info/WHEEL
ferrous_cat_finance-0.1.dist-info/licenses/LICENSE
ferrous_cat_finance-0.1.dist-info/RECORD
