Metadata-Version: 2.4
Name: ferrous_cat_finance
Version: 0.1
Summary: A program for recording and reporting on financial transactions, using Qt PySide6 for GUI and SQLite for a database.
Project-URL: Homepage, https://github.com/IsaacErb-Professional/ferrous-cat-finance-app
Author-email: Isaac Erb <isaac.n.erb@gmail.com>, Nelson Erb <nelson.erb@gmail.com>
License-File: LICENSE
Classifier: Development Status :: 3 - Alpha
Classifier: Intended Audience :: End Users/Desktop
Classifier: License :: OSI Approved :: GNU General Public License v3 (GPLv3)
Classifier: Operating System :: MacOS :: MacOS X
Classifier: Operating System :: POSIX :: Linux
Classifier: Programming Language :: Python :: 3.10
Classifier: Programming Language :: Python :: 3.11
Classifier: Programming Language :: SQL
Classifier: Topic :: Database
Requires-Python: >=3.10
